CHANGES.rst
LICENSE
MANIFEST.in
README.rst
requirements.txt
setup.py
ttop/__init__.py
ttop/color.py
ttop/core.py
ttop/tmux.py
ttop/ttop.py
ttop/view.py
ttop.egg-info/PKG-INFO
ttop.egg-info/SOURCES.txt
ttop.egg-info/dependency_links.txt
ttop.egg-info/entry_points.txt
ttop.egg-info/requires.txt
ttop.egg-info/top_level.txt